{
    "project_name": "Data_science_template Project",
	"description": "A short description of the data_science_template project.",
    "repo_name": "{{ cookiecutter.project_name.lower().replace(' ', '_') }}",
    "author_name": "Your Name(s) (multiple authors can be added by using a ';' delimiter)",
	"orcid": "Provide your ORCID (multiple ORCID can be added by using a ';' delimiter)",
	"version": "0.0.1",
    "open_source_license": ["MIT", "BSD-3-Clause", "None"],
	"programming_language":["Python","R","Stata (Pre-installation required)","Matlab (Pre-installation required)","SAS (Pre-installation required)","Other","None"],
	"environment_manager":["Conda","Venv","Virtualenv","None"],
	"version_control":["Git","Datalad","DVC","None"],
	"remote_storage": ["Dropbox","Deic Storage","Local Path","None"],
    "code_repository": ["GitHub","GitLab","None"]
}
